mustache/__init__.py
mustache/bowtie2tools.py
mustache/bwatools.py
mustache/config.py
mustache/embosstools.py
mustache/extendpairs.py
mustache/fastatools.py
mustache/findflanks.py
mustache/flanktrie.py
mustache/formatbam.py
mustache/help.py
mustache/inferseqassembly.py
mustache/inferseqdatabase.py
mustache/inferseqoverlap.py
mustache/inferseqreference.py
mustache/main.py
mustache/minimustools.py
mustache/misc.py
mustache/pairflanks.py
mustache/pysamtools.py
mustache/recall.py
mustache/samtools.py
mustache/sctools.py
bio_mustache-0.3.1.dist-info/LICENSE
bio_mustache-0.3.1.dist-info/METADATA
bio_mustache-0.3.1.dist-info/WHEEL
bio_mustache-0.3.1.dist-info/entry_points.txt
bio_mustache-0.3.1.dist-info/top_level.txt
bio_mustache-0.3.1.dist-info/RECORD
